{
  "kind": "spec_vs_diff_report",
  "version": "1.0",
  "generatedAt": "2026-03-01T23:18:37.807Z",
  "summary": "The diff implements all four requirements comprehensively. A LanguageContext provider (REQ-1) is created with localStorage persistence and English default. A language switcher is added to Header for both desktop and mobile layouts (REQ-2). A centralized translations file is created covering all components (REQ-3). All page-section components are updated to consume translations (REQ-4). Minor concerns: the translations file is truncated so completeness of all three languages for all components cannot be fully verified, and keyboard navigability of the switcher (aria-pressed is present but full keyboard nav is not confirmed). Overall implementation appears complete.",
  "missing_requirements": [],
  "hallucinated_features": [],
  "confidence": 0.85,
  "changed_files": [
    "frontend/src/App.tsx",
    "frontend/src/components/BankFinanceBanner.tsx",
    "frontend/src/components/FloatingWhatsAppButton.tsx",
    "frontend/src/components/Footer.tsx",
    "frontend/src/components/Header.tsx",
    "frontend/src/components/Hero.tsx",
    "frontend/src/components/InquiryForm.tsx",
    "frontend/src/components/OdishaGuide.tsx",
    "frontend/src/components/SchemeInfo.tsx",
    "frontend/src/components/Services.tsx",
    "frontend/src/components/WarrantyGuarantee.tsx",
    "frontend/src/components/WhatsAppSection.tsx",
    "frontend/src/components/WhyChooseUs.tsx",
    "frontend/src/contexts/LanguageContext.tsx",
    "frontend/src/i18n/translations.ts",
    "frontend/src/i18n/useTranslation.ts",
    "project_state.json"
  ]
}